pypro/__init__.py
pypro/app.py
pypro/cli.py
pypro/cli_simplified.py
pypro/db.py
pypro/middleware.py
pypro/plugins.py
pypro/routing.py
pypro/security.py
pypro/templating.py
pypro/types.py
pypro/utils.py
pypro/templates/base.html
pypro/templates/error.html
tests/__init__.py
tests/test_basic.py
pypro_framework-0.1.0.dist-info/LICENSE
pypro_framework-0.1.0.dist-info/METADATA
pypro_framework-0.1.0.dist-info/WHEEL
pypro_framework-0.1.0.dist-info/entry_points.txt
pypro_framework-0.1.0.dist-info/top_level.txt
pypro_framework-0.1.0.dist-info/RECORD
